{
  "cart": [
    {
      "items": [
        {
          "id": 2,
          "city": "Delhi",
          "name": "The G.T. ROAD",
          "area": "Central Delhi",
          "address": "Connaught Place",
          "rating": 4,
          "image": "https://im1.dineout.co.in/images/uploads/restaurant/sharpen/3/m/u/p31393-15972091555f337a43bb961.jpg?tr=tr:n-large",
          "discount": 15,
          "about": "Local, situated in the heart of the capital, is a colossal beauty for all party lovers. It is the epitome of class and elegance, with interiors adorned by paintings of monuments in Delhi, the space is just beautiful. Serving some of the best North Indian and Continental dishes from its affordable menu, Local makes it a worthwhile visit for one and all. The exclusive bar menu also offers an array of drinks and fine spirits to choose from. Be it getting into the party zone or spending some good time with your friends or unwinding with your colleagues, Local is where you can head to for some unadulterated happiness! The additional feature is the DJ nights hosted there which makes everyone groove on the dance floor. Local is located in Scindia House in Connaught Place, Delhi. ",
          "averageCost": "₹ 1,400 for 2",
          "cuisine": ["North Indian"],
          "menu": "https://im1.dineout.co.in/images/uploads/restaurant/sharpen/3/n/f/m31393-16455308776214cefda4a10.jpg?tr=tr:n-xlarge",
          "type": ["Casual Dining"],
          "bestSellingItems": [
            "Paan Cosmo",
            "Local LIIT",
            "Chai Ka Punch",
            "Aam Mojito",
            "Punjabi Old Fashion",
            "Farmer Vegetable Pizza",
            "Loaded Cheese Nachos",
            "Fish Finger Skewers"
          ],
          "facilities": [
            {
              "WiFi": "https://im1.dineout.co.in/images/uploads/misc/2019/Jul/1/8.png"
            },
            {
              "Air Conditioned": "https://im1.dineout.co.in/images/uploads/misc/2019/Jul/1/7.png"
            },
            {
              "Valet Available": "https://im1.dineout.co.in/images/uploads/misc/2019/Jul/1/21.png"
            },
            {
              "Parking": "https://im1.dineout.co.in/images/uploads/misc/2019/Jul/1/11.png"
            },
            {
              "Card Accepted": "https://im1.dineout.co.in/images/uploads/misc/2019/Jul/1/13.png"
            },
            {
              "Wallet Accepted": "https://im1.dineout.co.in/images/uploads/misc/2019/Jul/1/2.png"
            }
          ],
          "callUs": ["+91 9212340202", "09999477661"],
          "reviews": [
            {
              "name": "Aarjav Jain",
              "star": 4,
              "head": "Disliked: Food",
              "reviewPost": "I think they should also focus on their menu. there is no variety of food and drinks."
            },
            {
              "name": "Dr Tushar",
              "star": 3,
              "head": "Liked: Music",
              "reviewPost": "Nice experience"
            }
          ]
        },
        {
          "id": 1,
          "city": "Delhi",
          "name": "Tamasha",
          "area": "Central Delhi",
          "address": "Connaught Place",
          "rating": 4.2,
          "image": "https://im1.dineout.co.in/images/uploads/restaurant/sharpen/2/a/j/p20996-145631488756cd9a0796608.jpg?tr=tr:n-large",
          "discount": 0,
          "about": "Tamasha is one of the most popular places to hang out in Heart of Delhi-CP. This Restaurant has Distinct Seating Areas including a Courtyard, Ground Floor, First Floor, Backyard and an Amazing Rooftop over spacious ambience. Tamasha offers multi-cuisine dishes from North Indian, Italian, Continental and Asian cuisines and an array of Finger Food. Tamasha is an ideal place for a Night Out Friends or good times with Family Members. The eye-catching bar is built to resemble Optimus Prime, a fictional character from the Transformers Franchise. This is a super awesome place which is definitely worth going for one and all! ",
          "averageCost": "₹ 1,800 for 2",
          "cuisine": [
            "Continental",
            "Finger Food",
            "North Indian",
            "Italian",
            "Asian"
          ],
          "menu": "https://im1.dineout.co.in/images/uploads/restaurant/sharpen/2/y/q/m20996-15585052765ce4e73c57b3c.jpg?tr=tr:n-xlarge",
          "type": ["Lounge", "Nightlife", "Bar"],
          "bestSellingItems": [
            "Dahi Kebab",
            "Dragon Roll",
            "Alfredo Penne",
            "Golden Prawns",
            "Phuket Fish",
            "Chicken Chettinad"
          ],
          "facilities": [
            [
              "Smoking Area",
              "https://im1.dineout.co.in/images/uploads/misc/2019/Jul/1/17.png"
            ],
            [
              "Air Conditioned",
              "https://im1.dineout.co.in/images/uploads/misc/2019/Jul/1/7.png"
            ],
            [
              "Valet Available",
              "https://im1.dineout.co.in/images/uploads/misc/2019/Jul/1/21.png"
            ],
            [
              "Parking",
              "https://im1.dineout.co.in/images/uploads/misc/2019/Jul/1/11.png"
            ],
            [
              "Live Performance",
              "https://im1.dineout.co.in/images/uploads/misc/2019/Jul/1/27.png"
            ],
            [
              "Card Accepted",
              "https://im1.dineout.co.in/images/uploads/misc/2019/Jul/1/13.png"
            ],
            [
              "Full Bar Available",
              "https://im1.dineout.co.in/images/uploads/misc/2019/Jul/1/15.png"
            ],
            [
              "Outdoor Seating",
              "https://im1.dineout.co.in/images/uploads/misc/2019/Jul/1/16.png"
            ],
            [
              "Live Screening",
              "https://im1.dineout.co.in/images/uploads/misc/2019/Jul/1/1.png"
            ],
            [
              "Wallet Accepted",
              "https://im1.dineout.co.in/images/uploads/misc/2019/Jul/1/2.png"
            ]
          ],
          "callUs": ["+91 9212340202", "09999477661"],
          "reviews": [
            {
              "name": "Antriksh",
              "star": 3,
              "head": "Could be better: Ambience",
              "reviewPost": "no sanitizers were there on tables.. washroom is also bit unhygienic"
            },
            {
              "name": "Amit Talwar",
              "star": 3,
              "head": "Could be better: Ambience",
              "reviewPost": "Not that good ok ok"
            }
          ]
        },
        {
          "id": 4,
          "city": "Delhi",
          "name": "Boa Village",
          "area": "North Delhi",
          "address": "Civil Lines",
          "rating": 4.4,
          "image": "https://im1.dineout.co.in/images/uploads/restaurant/sharpen/2/a/k/p21335-1481348699584b965b9a990.jpg?tr=tr:n-large",
          "discount": 30,
          "about": "Bao Village is situated in the posh locality of Civil Lines, where you can tantalize your senses with the aroma of Chinese, Japanese, Asian, and Korean Cuisines. The place has a beautiful outdoor seating space and a dining area. The high-end liquor, smoothies, and cocktails paired up with Live Music and Match Screening take you to a joyful journey like never before. The nearest landmark of Bao Village is Civil Lines Metro Station Gate No.3. ",
          "averageCost": "₹ 2,500 for 2",
          "cuisine": ["Continental", "Thai", "Japanese", "Asian"],
          "menu": "https://im1.dineout.co.in/images/uploads/restaurant/sharpen/2/q/i/m21335-16341255196166c6cfce0da.jpg?tr=tr:n-xlarge",
          "type": ["Nightlife"],
          "bestSellingItems": [
            "Corn Potato",
            "Chicken Tempura",
            "Soya Nuggets",
            "Banana Toffee",
            "Bellini",
            "Salmon Sushi"
          ],
          "facilities": [
            {
              "Smoking Area": "https://im1.dineout.co.in/images/uploads/misc/2019/Jul/1/17.png"
            },
            {
              "Air Conditioned": "https://im1.dineout.co.in/images/uploads/misc/2019/Jul/1/7.png"
            },
            {
              "Valet Available": "https://im1.dineout.co.in/images/uploads/misc/2019/Jul/1/21.png"
            },
            {
              "Parking": "https://im1.dineout.co.in/images/uploads/misc/2019/Jul/1/11.png"
            },
            {
              "Card Accepted": "https://im1.dineout.co.in/images/uploads/misc/2019/Jul/1/13.png"
            },
            {
              "Full Bar Available": "https://im1.dineout.co.in/images/uploads/misc/2019/Jul/1/15.png"
            },
            {
              "Live Screening": "https://im1.dineout.co.in/images/uploads/misc/2019/Jul/1/1.png"
            },
            {
              "Wallet Accepted": "https://im1.dineout.co.in/images/uploads/misc/2019/Jul/1/2.png"
            },
            {
              "Home Delivery": "https://im1.dineout.co.in/images/uploads/misc/2019/Jul/1/9.png"
            },
            {
              "Lift": "https://im1.dineout.co.in/images/uploads/misc/2019/Jul/1/18.png"
            },
            {
              "Dance Floor": "https://im1.dineout.co.in/images/uploads/misc/2019/Jul/1/30.png"
            },
            {
              "DJ": "https://im1.dineout.co.in/images/uploads/misc/2019/Jul/1/19.png"
            },
            {
              "Roof Top": "https://im1.dineout.co.in/images/uploads/misc/2019/Jul/1/19.png"
            }
          ],
          "callUs": ["+91 9212340202", "09999477661"],
          "reviews": [
            {
              "name": "Rakhi Khattar",
              "star": 2,
              "head": "Disliked: Food",
              "reviewPost": "I think they should also focus on their menu. there is no variety of food and drinks."
            },
            {
              "name": "Dr Tushar",
              "star": 3,
              "head": "Liked: Service",
              "reviewPost": "all was awesome !!"
            }
          ]
        },
        {
          "id": 4,
          "city": "Delhi",
          "name": "Boa Village",
          "area": "North Delhi",
          "address": "Civil Lines",
          "rating": 4.4,
          "image": "https://im1.dineout.co.in/images/uploads/restaurant/sharpen/2/a/k/p21335-1481348699584b965b9a990.jpg?tr=tr:n-large",
          "discount": 30,
          "about": "Bao Village is situated in the posh locality of Civil Lines, where you can tantalize your senses with the aroma of Chinese, Japanese, Asian, and Korean Cuisines. The place has a beautiful outdoor seating space and a dining area. The high-end liquor, smoothies, and cocktails paired up with Live Music and Match Screening take you to a joyful journey like never before. The nearest landmark of Bao Village is Civil Lines Metro Station Gate No.3. ",
          "averageCost": "₹ 2,500 for 2",
          "cuisine": ["Continental", "Thai", "Japanese", "Asian"],
          "menu": "https://im1.dineout.co.in/images/uploads/restaurant/sharpen/2/q/i/m21335-16341255196166c6cfce0da.jpg?tr=tr:n-xlarge",
          "type": ["Nightlife"],
          "bestSellingItems": [
            "Corn Potato",
            "Chicken Tempura",
            "Soya Nuggets",
            "Banana Toffee",
            "Bellini",
            "Salmon Sushi"
          ],
          "facilities": [
            {
              "Smoking Area": "https://im1.dineout.co.in/images/uploads/misc/2019/Jul/1/17.png"
            },
            {
              "Air Conditioned": "https://im1.dineout.co.in/images/uploads/misc/2019/Jul/1/7.png"
            },
            {
              "Valet Available": "https://im1.dineout.co.in/images/uploads/misc/2019/Jul/1/21.png"
            },
            {
              "Parking": "https://im1.dineout.co.in/images/uploads/misc/2019/Jul/1/11.png"
            },
            {
              "Card Accepted": "https://im1.dineout.co.in/images/uploads/misc/2019/Jul/1/13.png"
            },
            {
              "Full Bar Available": "https://im1.dineout.co.in/images/uploads/misc/2019/Jul/1/15.png"
            },
            {
              "Live Screening": "https://im1.dineout.co.in/images/uploads/misc/2019/Jul/1/1.png"
            },
            {
              "Wallet Accepted": "https://im1.dineout.co.in/images/uploads/misc/2019/Jul/1/2.png"
            },
            {
              "Home Delivery": "https://im1.dineout.co.in/images/uploads/misc/2019/Jul/1/9.png"
            },
            {
              "Lift": "https://im1.dineout.co.in/images/uploads/misc/2019/Jul/1/18.png"
            },
            {
              "Dance Floor": "https://im1.dineout.co.in/images/uploads/misc/2019/Jul/1/30.png"
            },
            {
              "DJ": "https://im1.dineout.co.in/images/uploads/misc/2019/Jul/1/19.png"
            },
            {
              "Roof Top": "https://im1.dineout.co.in/images/uploads/misc/2019/Jul/1/19.png"
            }
          ],
          "callUs": ["+91 9212340202", "09999477661"],
          "reviews": [
            {
              "name": "Rakhi Khattar",
              "star": 2,
              "head": "Disliked: Food",
              "reviewPost": "I think they should also focus on their menu. there is no variety of food and drinks."
            },
            {
              "name": "Dr Tushar",
              "star": 3,
              "head": "Liked: Service",
              "reviewPost": "all was awesome !!"
            }
          ]
        },
        {
          "id": 1,
          "city": "Delhi",
          "name": "Tamasha",
          "area": "Central Delhi",
          "address": "Connaught Place",
          "rating": 4.2,
          "image": "https://im1.dineout.co.in/images/uploads/restaurant/sharpen/2/a/j/p20996-145631488756cd9a0796608.jpg?tr=tr:n-large",
          "discount": 0,
          "about": "Tamasha is one of the most popular places to hang out in Heart of Delhi-CP. This Restaurant has Distinct Seating Areas including a Courtyard, Ground Floor, First Floor, Backyard and an Amazing Rooftop over spacious ambience. Tamasha offers multi-cuisine dishes from North Indian, Italian, Continental and Asian cuisines and an array of Finger Food. Tamasha is an ideal place for a Night Out Friends or good times with Family Members. The eye-catching bar is built to resemble Optimus Prime, a fictional character from the Transformers Franchise. This is a super awesome place which is definitely worth going for one and all! ",
          "averageCost": "₹ 1,800 for 2",
          "cuisine": [
            "Continental",
            "Finger Food",
            "North Indian",
            "Italian",
            "Asian"
          ],
          "menu": "https://im1.dineout.co.in/images/uploads/restaurant/sharpen/2/y/q/m20996-15585052765ce4e73c57b3c.jpg?tr=tr:n-xlarge",
          "type": ["Lounge", "Nightlife", "Bar"],
          "bestSellingItems": [
            "Dahi Kebab",
            "Dragon Roll",
            "Alfredo Penne",
            "Golden Prawns",
            "Phuket Fish",
            "Chicken Chettinad"
          ],
          "facilities": [
            [
              "Smoking Area",
              "https://im1.dineout.co.in/images/uploads/misc/2019/Jul/1/17.png"
            ],
            [
              "Air Conditioned",
              "https://im1.dineout.co.in/images/uploads/misc/2019/Jul/1/7.png"
            ],
            [
              "Valet Available",
              "https://im1.dineout.co.in/images/uploads/misc/2019/Jul/1/21.png"
            ],
            [
              "Parking",
              "https://im1.dineout.co.in/images/uploads/misc/2019/Jul/1/11.png"
            ],
            [
              "Live Performance",
              "https://im1.dineout.co.in/images/uploads/misc/2019/Jul/1/27.png"
            ],
            [
              "Card Accepted",
              "https://im1.dineout.co.in/images/uploads/misc/2019/Jul/1/13.png"
            ],
            [
              "Full Bar Available",
              "https://im1.dineout.co.in/images/uploads/misc/2019/Jul/1/15.png"
            ],
            [
              "Outdoor Seating",
              "https://im1.dineout.co.in/images/uploads/misc/2019/Jul/1/16.png"
            ],
            [
              "Live Screening",
              "https://im1.dineout.co.in/images/uploads/misc/2019/Jul/1/1.png"
            ],
            [
              "Wallet Accepted",
              "https://im1.dineout.co.in/images/uploads/misc/2019/Jul/1/2.png"
            ]
          ],
          "callUs": ["+91 9212340202", "09999477661"],
          "reviews": [
            {
              "name": "Antriksh",
              "star": 3,
              "head": "Could be better: Ambience",
              "reviewPost": "no sanitizers were there on tables.. washroom is also bit unhygienic"
            },
            {
              "name": "Amit Talwar",
              "star": 3,
              "head": "Could be better: Ambience",
              "reviewPost": "Not that good ok ok"
            }
          ]
        },
        {
          "id": 1,
          "city": "Delhi",
          "name": "Tamasha",
          "area": "Central Delhi",
          "address": "Connaught Place",
          "rating": 4.2,
          "image": "https://im1.dineout.co.in/images/uploads/restaurant/sharpen/2/a/j/p20996-145631488756cd9a0796608.jpg?tr=tr:n-large",
          "discount": 0,
          "about": "Tamasha is one of the most popular places to hang out in Heart of Delhi-CP. This Restaurant has Distinct Seating Areas including a Courtyard, Ground Floor, First Floor, Backyard and an Amazing Rooftop over spacious ambience. Tamasha offers multi-cuisine dishes from North Indian, Italian, Continental and Asian cuisines and an array of Finger Food. Tamasha is an ideal place for a Night Out Friends or good times with Family Members. The eye-catching bar is built to resemble Optimus Prime, a fictional character from the Transformers Franchise. This is a super awesome place which is definitely worth going for one and all! ",
          "averageCost": "₹ 1,800 for 2",
          "cuisine": [
            "Continental",
            "Finger Food",
            "North Indian",
            "Italian",
            "Asian"
          ],
          "menu": "https://im1.dineout.co.in/images/uploads/restaurant/sharpen/2/y/q/m20996-15585052765ce4e73c57b3c.jpg?tr=tr:n-xlarge",
          "type": ["Lounge", "Nightlife", "Bar"],
          "bestSellingItems": [
            "Dahi Kebab",
            "Dragon Roll",
            "Alfredo Penne",
            "Golden Prawns",
            "Phuket Fish",
            "Chicken Chettinad"
          ],
          "facilities": [
            [
              "Smoking Area",
              "https://im1.dineout.co.in/images/uploads/misc/2019/Jul/1/17.png"
            ],
            [
              "Air Conditioned",
              "https://im1.dineout.co.in/images/uploads/misc/2019/Jul/1/7.png"
            ],
            [
              "Valet Available",
              "https://im1.dineout.co.in/images/uploads/misc/2019/Jul/1/21.png"
            ],
            [
              "Parking",
              "https://im1.dineout.co.in/images/uploads/misc/2019/Jul/1/11.png"
            ],
            [
              "Live Performance",
              "https://im1.dineout.co.in/images/uploads/misc/2019/Jul/1/27.png"
            ],
            [
              "Card Accepted",
              "https://im1.dineout.co.in/images/uploads/misc/2019/Jul/1/13.png"
            ],
            [
              "Full Bar Available",
              "https://im1.dineout.co.in/images/uploads/misc/2019/Jul/1/15.png"
            ],
            [
              "Outdoor Seating",
              "https://im1.dineout.co.in/images/uploads/misc/2019/Jul/1/16.png"
            ],
            [
              "Live Screening",
              "https://im1.dineout.co.in/images/uploads/misc/2019/Jul/1/1.png"
            ],
            [
              "Wallet Accepted",
              "https://im1.dineout.co.in/images/uploads/misc/2019/Jul/1/2.png"
            ]
          ],
          "callUs": ["+91 9212340202", "09999477661"],
          "reviews": [
            {
              "name": "Antriksh",
              "star": 3,
              "head": "Could be better: Ambience",
              "reviewPost": "no sanitizers were there on tables.. washroom is also bit unhygienic"
            },
            {
              "name": "Amit Talwar",
              "star": 3,
              "head": "Could be better: Ambience",
              "reviewPost": "Not that good ok ok"
            }
          ]
        },
        {
          "id": 4,
          "city": "Delhi",
          "name": "Boa Village",
          "area": "North Delhi",
          "address": "Civil Lines",
          "rating": 4.4,
          "image": "https://im1.dineout.co.in/images/uploads/restaurant/sharpen/2/a/k/p21335-1481348699584b965b9a990.jpg?tr=tr:n-large",
          "discount": 30,
          "about": "Bao Village is situated in the posh locality of Civil Lines, where you can tantalize your senses with the aroma of Chinese, Japanese, Asian, and Korean Cuisines. The place has a beautiful outdoor seating space and a dining area. The high-end liquor, smoothies, and cocktails paired up with Live Music and Match Screening take you to a joyful journey like never before. The nearest landmark of Bao Village is Civil Lines Metro Station Gate No.3. ",
          "averageCost": "₹ 2,500 for 2",
          "cuisine": ["Continental", "Thai", "Japanese", "Asian"],
          "menu": "https://im1.dineout.co.in/images/uploads/restaurant/sharpen/2/q/i/m21335-16341255196166c6cfce0da.jpg?tr=tr:n-xlarge",
          "type": ["Nightlife"],
          "bestSellingItems": [
            "Corn Potato",
            "Chicken Tempura",
            "Soya Nuggets",
            "Banana Toffee",
            "Bellini",
            "Salmon Sushi"
          ],
          "facilities": [
            {
              "Smoking Area": "https://im1.dineout.co.in/images/uploads/misc/2019/Jul/1/17.png"
            },
            {
              "Air Conditioned": "https://im1.dineout.co.in/images/uploads/misc/2019/Jul/1/7.png"
            },
            {
              "Valet Available": "https://im1.dineout.co.in/images/uploads/misc/2019/Jul/1/21.png"
            },
            {
              "Parking": "https://im1.dineout.co.in/images/uploads/misc/2019/Jul/1/11.png"
            },
            {
              "Card Accepted": "https://im1.dineout.co.in/images/uploads/misc/2019/Jul/1/13.png"
            },
            {
              "Full Bar Available": "https://im1.dineout.co.in/images/uploads/misc/2019/Jul/1/15.png"
            },
            {
              "Live Screening": "https://im1.dineout.co.in/images/uploads/misc/2019/Jul/1/1.png"
            },
            {
              "Wallet Accepted": "https://im1.dineout.co.in/images/uploads/misc/2019/Jul/1/2.png"
            },
            {
              "Home Delivery": "https://im1.dineout.co.in/images/uploads/misc/2019/Jul/1/9.png"
            },
            {
              "Lift": "https://im1.dineout.co.in/images/uploads/misc/2019/Jul/1/18.png"
            },
            {
              "Dance Floor": "https://im1.dineout.co.in/images/uploads/misc/2019/Jul/1/30.png"
            },
            {
              "DJ": "https://im1.dineout.co.in/images/uploads/misc/2019/Jul/1/19.png"
            },
            {
              "Roof Top": "https://im1.dineout.co.in/images/uploads/misc/2019/Jul/1/19.png"
            }
          ],
          "callUs": ["+91 9212340202", "09999477661"],
          "reviews": [
            {
              "name": "Rakhi Khattar",
              "star": 2,
              "head": "Disliked: Food",
              "reviewPost": "I think they should also focus on their menu. there is no variety of food and drinks."
            },
            {
              "name": "Dr Tushar",
              "star": 3,
              "head": "Liked: Service",
              "reviewPost": "all was awesome !!"
            }
          ]
        }
      ],
      "changed": true,
      "id": 1
    }
  ],
  "navbarplacessearch": [
    {
      "Delhi": "Delhi",
      "Mumbai": "Mumbai",
      "Bangalore": "Bangalore",
      "Chennai": "Chennai",
      "Hyderabad": "Hyderabad",
      "Pune": "Pune",
      "kolkata": "Kolkata",
      "Ahmedabad": "Ahmedabad",
      "Chandigarh": "Chandigarh",
      "Goa": "Goa",
      "Jaipur": "Jaipur",
      "Lucknow": "Lucknow",
      "Indore": "Indore",
      "Udaipur": "Udaipur",
      "Agra": "Agra",
      "Vadodara": "Vadodara",
      "Nagpur": "Nagpur",
      "Kochi": "Kochi",
      "Surat": "Surat",
      "Ludhiana": "Ludhiana"
    }
  ],
  "posts": [
    {
      "id": 1,
      "city": "Delhi",
      "name": "Tamasha",
      "area": "Central Delhi",
      "address": "Connaught Place",
      "rating": 4.2,
      "image": "https://im1.dineout.co.in/images/uploads/restaurant/sharpen/2/a/j/p20996-145631488756cd9a0796608.jpg?tr=tr:n-large",
      "discount": 0,
      "about": "Tamasha is one of the most popular places to hang out in Heart of Delhi-CP. This Restaurant has Distinct Seating Areas including a Courtyard, Ground Floor, First Floor, Backyard and an Amazing Rooftop over spacious ambience. Tamasha offers multi-cuisine dishes from North Indian, Italian, Continental and Asian cuisines and an array of Finger Food. Tamasha is an ideal place for a Night Out Friends or good times with Family Members. The eye-catching bar is built to resemble Optimus Prime, a fictional character from the Transformers Franchise. This is a super awesome place which is definitely worth going for one and all! ",
      "averageCost": "₹ 1,800 for 2",
      "cuisine": [
        "Continental",
        "Finger Food",
        "North Indian",
        "Italian",
        "Asian"
      ],
      "menu": "https://im1.dineout.co.in/images/uploads/restaurant/sharpen/2/y/q/m20996-15585052765ce4e73c57b3c.jpg?tr=tr:n-xlarge",
      "type": ["Lounge", "Nightlife", "Bar"],
      "bestSellingItems": [
        "Dahi Kebab",
        "Dragon Roll",
        "Alfredo Penne",
        "Golden Prawns",
        "Phuket Fish",
        "Chicken Chettinad"
      ],
      "facilities": [
        [
          "Smoking Area",
          "https://im1.dineout.co.in/images/uploads/misc/2019/Jul/1/17.png"
        ],
        [
          "Air Conditioned",
          "https://im1.dineout.co.in/images/uploads/misc/2019/Jul/1/7.png"
        ],
        [
          "Valet Available",
          "https://im1.dineout.co.in/images/uploads/misc/2019/Jul/1/21.png"
        ],
        [
          "Parking",
          "https://im1.dineout.co.in/images/uploads/misc/2019/Jul/1/11.png"
        ],
        [
          "Live Performance",
          "https://im1.dineout.co.in/images/uploads/misc/2019/Jul/1/27.png"
        ],
        [
          "Card Accepted",
          "https://im1.dineout.co.in/images/uploads/misc/2019/Jul/1/13.png"
        ],
        [
          "Full Bar Available",
          "https://im1.dineout.co.in/images/uploads/misc/2019/Jul/1/15.png"
        ],
        [
          "Outdoor Seating",
          "https://im1.dineout.co.in/images/uploads/misc/2019/Jul/1/16.png"
        ],
        [
          "Live Screening",
          "https://im1.dineout.co.in/images/uploads/misc/2019/Jul/1/1.png"
        ],
        [
          "Wallet Accepted",
          "https://im1.dineout.co.in/images/uploads/misc/2019/Jul/1/2.png"
        ]
      ],
      "callUs": ["+91 9212340202", "09999477661"],
      "reviews": [
        {
          "name": "Antriksh",
          "star": 3,
          "head": "Could be better: Ambience",
          "reviewPost": "no sanitizers were there on tables.. washroom is also bit unhygienic"
        },
        {
          "name": "Amit Talwar",
          "star": 3,
          "head": "Could be better: Ambience",
          "reviewPost": "Not that good ok ok"
        }
      ]
    },
    {
      "id": 2,
      "city": "Delhi",
      "name": "The G.T. ROAD",
      "area": "Central Delhi",
      "address": "Connaught Place",
      "rating": 4,
      "image": "https://im1.dineout.co.in/images/uploads/restaurant/sharpen/3/m/u/p31393-15972091555f337a43bb961.jpg?tr=tr:n-large",
      "discount": 15,
      "about": "Local, situated in the heart of the capital, is a colossal beauty for all party lovers. It is the epitome of class and elegance, with interiors adorned by paintings of monuments in Delhi, the space is just beautiful. Serving some of the best North Indian and Continental dishes from its affordable menu, Local makes it a worthwhile visit for one and all. The exclusive bar menu also offers an array of drinks and fine spirits to choose from. Be it getting into the party zone or spending some good time with your friends or unwinding with your colleagues, Local is where you can head to for some unadulterated happiness! The additional feature is the DJ nights hosted there which makes everyone groove on the dance floor. Local is located in Scindia House in Connaught Place, Delhi. ",
      "averageCost": "₹ 1,400 for 2",
      "cuisine": ["North Indian"],
      "menu": "https://im1.dineout.co.in/images/uploads/restaurant/sharpen/3/n/f/m31393-16455308776214cefda4a10.jpg?tr=tr:n-xlarge",
      "type": ["Casual Dining"],
      "bestSellingItems": [
        "Paan Cosmo",
        "Local LIIT",
        "Chai Ka Punch",
        "Aam Mojito",
        "Punjabi Old Fashion",
        "Farmer Vegetable Pizza",
        "Loaded Cheese Nachos",
        "Fish Finger Skewers"
      ],
      "facilities": [
        {
          "WiFi": "https://im1.dineout.co.in/images/uploads/misc/2019/Jul/1/8.png"
        },
        {
          "Air Conditioned": "https://im1.dineout.co.in/images/uploads/misc/2019/Jul/1/7.png"
        },
        {
          "Valet Available": "https://im1.dineout.co.in/images/uploads/misc/2019/Jul/1/21.png"
        },
        {
          "Parking": "https://im1.dineout.co.in/images/uploads/misc/2019/Jul/1/11.png"
        },
        {
          "Card Accepted": "https://im1.dineout.co.in/images/uploads/misc/2019/Jul/1/13.png"
        },
        {
          "Wallet Accepted": "https://im1.dineout.co.in/images/uploads/misc/2019/Jul/1/2.png"
        }
      ],
      "callUs": ["+91 9212340202", "09999477661"],
      "reviews": [
        {
          "name": "Aarjav Jain",
          "star": 4,
          "head": "Disliked: Food",
          "reviewPost": "I think they should also focus on their menu. there is no variety of food and drinks."
        },
        {
          "name": "Dr Tushar",
          "star": 3,
          "head": "Liked: Music",
          "reviewPost": "Nice experience"
        }
      ]
    },
    {
      "id": 3,
      "city": "Delhi",
      "name": "Local",
      "area": "Central Delhi",
      "address": "Connaught Place",
      "rating": 4,
      "image": "https://im1.dineout.co.in/images/uploads/restaurant/sharpen/2/b/t/p27452-15020105505986dcb6d147f.jpg?tr=tr:n-large",
      "discount": 15,
      "about": "Local, situated in the heart of the capital, is a colossal beauty for all party lovers. It is the epitome of class and elegance, with interiors adorned by paintings of monuments in Delhi, the space is just beautiful. Serving some of the best North Indian and Continental dishes from its affordable menu, Local makes it a worthwhile visit for one and all. The exclusive bar menu also offers an array of drinks and fine spirits to choose from. Be it getting into the party zone or spending some good time with your friends or unwinding with your colleagues, Local is where you can head to for some unadulterated happiness! The additional feature is the DJ nights hosted there which makes everyone groove on the dance floor. Local is located in Scindia House in Connaught Place, Delhi. ",
      "averageCost": "₹ 2,000 for 2",
      "cuisine": ["Continental", "North Indian", "Italian", "Asian"],
      "menu": "https://im1.dineout.co.in/images/uploads/restaurant/sharpen/2/p/i/m27452-164087383961cdbf6f82e9a.jpg?tr=tr:n-xlarge",
      "type": ["Casual Dining", "Nightlife"],
      "bestSellingItems": [
        "Paan Cosmo",
        "Local LIIT",
        "Chai Ka Punch",
        "Aam Mojito",
        "Punjabi Old Fashion",
        "Farmer Vegetable Pizza",
        "Loaded Cheese Nachos",
        "Fish Finger Skewers"
      ],
      "facilities": [
        {
          "Smoking Area": "https://im1.dineout.co.in/images/uploads/misc/2019/Jul/1/17.png"
        },
        {
          "Air Conditioned": "https://im1.dineout.co.in/images/uploads/misc/2019/Jul/1/7.png"
        },
        {
          "Valet Available": "https://im1.dineout.co.in/images/uploads/misc/2019/Jul/1/21.png"
        },
        {
          "Parking": "https://im1.dineout.co.in/images/uploads/misc/2019/Jul/1/11.png"
        },
        {
          "Card Accepted": "https://im1.dineout.co.in/images/uploads/misc/2019/Jul/1/13.png"
        },
        {
          "Full Bar Available": "https://im1.dineout.co.in/images/uploads/misc/2019/Jul/1/15.png"
        },
        {
          "Live Screening": "https://im1.dineout.co.in/images/uploads/misc/2019/Jul/1/1.png"
        },
        {
          "Wallet Accepted": "https://im1.dineout.co.in/images/uploads/misc/2019/Jul/1/2.png"
        },
        {
          "Home Delivery": "https://im1.dineout.co.in/images/uploads/misc/2019/Jul/1/9.png"
        }
      ],
      "callUs": ["+91 9212340202", "09999477661"],
      "reviews": [
        {
          "name": "Aarjav Jain",
          "star": 4,
          "head": "Disliked: Food",
          "reviewPost": "I think they should also focus on their menu. there is no variety of food and drinks."
        },
        {
          "name": "Dr Tushar",
          "star": 3,
          "head": "Liked: Music",
          "reviewPost": "Nice experience"
        }
      ]
    },
    {
      "id": 4,
      "city": "Delhi",
      "name": "Boa Village",
      "area": "North Delhi",
      "address": "Civil Lines",
      "rating": 4.4,
      "image": "https://im1.dineout.co.in/images/uploads/restaurant/sharpen/2/a/k/p21335-1481348699584b965b9a990.jpg?tr=tr:n-large",
      "discount": 30,
      "about": "Bao Village is situated in the posh locality of Civil Lines, where you can tantalize your senses with the aroma of Chinese, Japanese, Asian, and Korean Cuisines. The place has a beautiful outdoor seating space and a dining area. The high-end liquor, smoothies, and cocktails paired up with Live Music and Match Screening take you to a joyful journey like never before. The nearest landmark of Bao Village is Civil Lines Metro Station Gate No.3. ",
      "averageCost": "₹ 2,500 for 2",
      "cuisine": ["Continental", "Thai", "Japanese", "Asian"],
      "menu": "https://im1.dineout.co.in/images/uploads/restaurant/sharpen/2/q/i/m21335-16341255196166c6cfce0da.jpg?tr=tr:n-xlarge",
      "type": ["Nightlife"],
      "bestSellingItems": [
        "Corn Potato",
        "Chicken Tempura",
        "Soya Nuggets",
        "Banana Toffee",
        "Bellini",
        "Salmon Sushi"
      ],
      "facilities": [
        {
          "Smoking Area": "https://im1.dineout.co.in/images/uploads/misc/2019/Jul/1/17.png"
        },
        {
          "Air Conditioned": "https://im1.dineout.co.in/images/uploads/misc/2019/Jul/1/7.png"
        },
        {
          "Valet Available": "https://im1.dineout.co.in/images/uploads/misc/2019/Jul/1/21.png"
        },
        {
          "Parking": "https://im1.dineout.co.in/images/uploads/misc/2019/Jul/1/11.png"
        },
        {
          "Card Accepted": "https://im1.dineout.co.in/images/uploads/misc/2019/Jul/1/13.png"
        },
        {
          "Full Bar Available": "https://im1.dineout.co.in/images/uploads/misc/2019/Jul/1/15.png"
        },
        {
          "Live Screening": "https://im1.dineout.co.in/images/uploads/misc/2019/Jul/1/1.png"
        },
        {
          "Wallet Accepted": "https://im1.dineout.co.in/images/uploads/misc/2019/Jul/1/2.png"
        },
        {
          "Home Delivery": "https://im1.dineout.co.in/images/uploads/misc/2019/Jul/1/9.png"
        },
        {
          "Lift": "https://im1.dineout.co.in/images/uploads/misc/2019/Jul/1/18.png"
        },
        {
          "Dance Floor": "https://im1.dineout.co.in/images/uploads/misc/2019/Jul/1/30.png"
        },
        {
          "DJ": "https://im1.dineout.co.in/images/uploads/misc/2019/Jul/1/19.png"
        },
        {
          "Roof Top": "https://im1.dineout.co.in/images/uploads/misc/2019/Jul/1/19.png"
        }
      ],
      "callUs": ["+91 9212340202", "09999477661"],
      "reviews": [
        {
          "name": "Rakhi Khattar",
          "star": 2,
          "head": "Disliked: Food",
          "reviewPost": "I think they should also focus on their menu. there is no variety of food and drinks."
        },
        {
          "name": "Dr Tushar",
          "star": 3,
          "head": "Liked: Service",
          "reviewPost": "all was awesome !!"
        }
      ]
    },
    {
      "id": 5,
      "city": "Delhi",
      "name": "October",
      "area": "Noida",
      "address": "Sector 119",
      "rating": 4.4,
      "image": "https://im1.dineout.co.in/images/uploads/restaurant/sharpen/1/s/q/p103643-164396900661fcf9ee9c260.jpg?tr=tr:n-large",
      "discount": 15,
      "about": "October is a perfect getaway from the mundane flow of life, bringing alive the very essence of the pub culture made famous by the typical pubs of Europe, offering a place to connect with friends, conversations, awesome food and drinks, in an ambiance that lets you relax and go with the flow. This brand new urban spin of pub culture arrives at the capital. Take a trip to The Chatter House, a welcome ambiance that immediately transports you to another level. The outlet is located in Khan Market, Delhi. ",
      "averageCost": "₹ 1,500 for 2",
      "cuisine": ["Continental", "North Indian", "Asian"],
      "menu": "https://im1.dineout.co.in/images/uploads/restaurant/sharpen/1/b/e/m103643-164396881561fcf92f6f642.jpg?tr=tr:n-xlarge",
      "type": ["Casual Dining"],
      "bestSellingItems": [
        "Corn Potato",
        "Chicken Tempura",
        "Bellini",
        "Salmon Sushi",
        "Tiramisu",
        "Blueberry Lemon Cake",
        "Chiken Burger"
      ],
      "facilities": [
        {
          "Smoking Area": "https://im1.dineout.co.in/images/uploads/misc/2019/Jul/1/17.png"
        },
        {
          "Air Conditioned": "https://im1.dineout.co.in/images/uploads/misc/2019/Jul/1/7.png"
        },
        {
          "Valet Available": "https://im1.dineout.co.in/images/uploads/misc/2019/Jul/1/21.png"
        },
        {
          "Parking": "https://im1.dineout.co.in/images/uploads/misc/2019/Jul/1/11.png"
        },
        {
          "Card Accepted": "https://im1.dineout.co.in/images/uploads/misc/2019/Jul/1/13.png"
        },
        {
          "Wallet Accepted": "https://im1.dineout.co.in/images/uploads/misc/2019/Jul/1/2.png"
        },
        {
          "Dance Floor": "https://im1.dineout.co.in/images/uploads/misc/2019/Jul/1/30.png"
        },
        {
          "DJ": "https://im1.dineout.co.in/images/uploads/misc/2019/Jul/1/19.png"
        }
      ],
      "callUs": ["+91 9212340202", "0120-3101000"],
      "reviews": [
        {
          "name": "Dhruv Jindal",
          "star": 5,
          "head": "Liked: Ambience",
          "reviewPost": "Good food"
        },
        {
          "name": "Dr Tushar",
          "star": 3,
          "head": "Liked: Service",
          "reviewPost": "all was awesome !!"
        }
      ]
    },
    {
      "id": 6,
      "city": "Delhi",
      "name": "Duty Free",
      "area": "West Delhi",
      "address": "Rajouri Garden",
      "rating": 4.4,
      "image": "https://im1.dineout.co.in/images/uploads/restaurant/sharpen/3/c/k/p37962-15268826035b02612bcd1b8.jpg?tr=tr:n-large",
      "discount": 20,
      "about": "Duty Free is a perfect getaway from the mundane flow of life, bringing alive the very essence of the pub culture made famous by the typical pubs of Europe, offering a place to connect with friends, conversations, awesome food and drinks, in an ambiance that lets you relax and go with the flow. This brand new urban spin of pub culture arrives at the capital. Take a trip to The Chatter House, a welcome ambiance that immediately transports you to another level. The outlet is located in Khan Market, Delhi. ",
      "averageCost": "₹ 1,500 for 2",
      "cuisine": ["Continental", "North Indian", "Asian", "Mexican"],
      "menu": "https://im1.dineout.co.in/images/uploads/restaurant/sharpen/3/g/g/m37962-164158013661d88668437b5.jpg?tr=tr:n-xlarge",
      "type": ["Casual Dining", "Bar"],
      "bestSellingItems": [
        "Dahi ke Sholay",
        "Butter Chicken",
        "Chicken Tempura",
        "Bellini",
        "Salmon Sushi",
        "Tiramisu",
        "Blueberry Lemon Cake",
        "Chiken Burger"
      ],
      "facilities": [
        {
          "Smoking Area": "https://im1.dineout.co.in/images/uploads/misc/2019/Jul/1/17.png"
        },
        {
          "Air Conditioned": "https://im1.dineout.co.in/images/uploads/misc/2019/Jul/1/7.png"
        },
        {
          "Valet Available": "https://im1.dineout.co.in/images/uploads/misc/2019/Jul/1/21.png"
        },
        {
          "Parking": "https://im1.dineout.co.in/images/uploads/misc/2019/Jul/1/11.png"
        },
        {
          "Card Accepted": "https://im1.dineout.co.in/images/uploads/misc/2019/Jul/1/13.png"
        },
        {
          "Wallet Accepted": "https://im1.dineout.co.in/images/uploads/misc/2019/Jul/1/2.png"
        },
        {
          "Serves Alcohol": "https://im1.dineout.co.in/images/uploads/misc/2019/Jul/1/10.png"
        }
      ],
      "callUs": ["+91 9212340202", "0120-3101000"],
      "reviews": [
        {
          "name": "Dhruv Jindal",
          "star": 5,
          "head": "Liked: Ambience",
          "reviewPost": "Good food"
        },
        {
          "name": "Dr Tushar",
          "star": 3,
          "head": "Liked: Service",
          "reviewPost": "all was awesome !!"
        }
      ]
    },
    {
      "id": 7,
      "city": "Delhi",
      "name": "TOS - Take Off Scarlet",
      "area": "West Delhi",
      "address": "Panjabi Bagh",
      "rating": 4.4,
      "image": "https://im1.dineout.co.in/images/uploads/restaurant/sharpen/2/v/k/p23764-16118396646012b8b01badf.jpg?tr=tr:n-large",
      "discount": 0,
      "about": "Take Off Scarlet is a perfect getaway from the mundane flow of life, bringing alive the very essence of the pub culture made famous by the typical pubs of Europe, offering a place to connect with friends, conversations, awesome food and drinks, in an ambiance that lets you relax and go with the flow. This brand new urban spin of pub culture arrives at the capital. Take a trip to The Chatter House, a welcome ambiance that immediately transports you to another level. The outlet is located in Khan Market, Delhi. ",
      "averageCost": "₹ 1,500 for 2",
      "cuisine": ["Continental", "North Indian"],
      "menu": "https://im1.dineout.co.in/images/uploads/restaurant/sharpen/2/r/u/m23764-16100039105ff6b5c6f2b1e.jpg?tr=tr:n-xlarge",
      "type": ["NightLife", "Bar"],
      "bestSellingItems": [
        "Dahi ke Sholay",
        "Butter Chicken",
        "Chicken Tempura",
        "Bellini",
        "Salmon Sushi",
        "Keema Fries",
        "Blueberry Lemon Cake",
        "Chiken Burger"
      ],
      "facilities": [
        {
          "Smoking Area": "https://im1.dineout.co.in/images/uploads/misc/2019/Jul/1/17.png"
        },
        {
          "Air Conditioned": "https://im1.dineout.co.in/images/uploads/misc/2019/Jul/1/7.png"
        },
        {
          "Valet Available": "https://im1.dineout.co.in/images/uploads/misc/2019/Jul/1/21.png"
        },
        {
          "Parking": "https://im1.dineout.co.in/images/uploads/misc/2019/Jul/1/11.png"
        },
        {
          "Card Accepted": "https://im1.dineout.co.in/images/uploads/misc/2019/Jul/1/13.png"
        },
        {
          "Wallet Accepted": "https://im1.dineout.co.in/images/uploads/misc/2019/Jul/1/2.png"
        },
        {
          "Serves Alcohol": "https://im1.dineout.co.in/images/uploads/misc/2019/Jul/1/10.png"
        },
        {
          "Dance Floor": "https://im1.dineout.co.in/images/uploads/misc/2019/Jul/1/30.png"
        },
        {
          "DJ": "https://im1.dineout.co.in/images/uploads/misc/2019/Jul/1/19.png"
        },
        {
          "Roof Top": "https://im1.dineout.co.in/images/uploads/misc/2019/Jul/1/19.png"
        }
      ],
      "callUs": ["+91 9212340202", "0120-3101000"],
      "reviews": [
        {
          "name": "Dhruv Jindal",
          "star": 5,
          "head": "Liked: Ambience",
          "reviewPost": "Good food"
        },
        {
          "name": "Dr Tushar",
          "star": 3,
          "head": "Liked: Service",
          "reviewPost": "all was awesome !!"
        }
      ]
    },
    {
      "id": 8,
      "city": "Delhi",
      "name": "Dwarka SYD",
      "area": "West Delhi",
      "address": "Panjabi Bagh",
      "rating": 4.4,
      "image": "https://im1.dineout.co.in/images/uploads/restaurant/sharpen/1/u/p/p103995-1645450034621393323a023.jpg?tr=tr:n-large",
      "discount": 30,
      "about": "Dwarka SYD is a perfect getaway from the mundane flow of life, bringing alive the very essence of the pub culture made famous by the typical pubs of Europe, offering a place to connect with friends, conversations, awesome food and drinks, in an ambiance that lets you relax and go with the flow. This brand new urban spin of pub culture arrives at the capital. Take a trip to The Chatter House, a welcome ambiance that immediately transports you to another level. The outlet is located in Khan Market, Delhi. ",
      "averageCost": "₹ 900 for 2",
      "cuisine": ["Continental", "North Indian", "American", "Chinese"],
      "menu": "https://im1.dineout.co.in/images/uploads/restaurant/sharpen/1/t/k/m103995-1645449953621392e12d9e9.jpg?tr=tr:n-xlarge",
      "type": ["NightLife", "Bar"],
      "bestSellingItems": [
        "Exotic Mushroom",
        "Butter Chicken",
        "Gulab Jamun",
        "Kadhai Paneer",
        "Cottage Chesse Burger",
        "Keema Fries",
        "Blueberry Lemon Cake",
        "Chiken Burger"
      ],
      "facilities": [
        {
          "Smoking Area": "https://im1.dineout.co.in/images/uploads/misc/2019/Jul/1/17.png"
        },
        {
          "Air Conditioned": "https://im1.dineout.co.in/images/uploads/misc/2019/Jul/1/7.png"
        },
        {
          "Valet Available": "https://im1.dineout.co.in/images/uploads/misc/2019/Jul/1/21.png"
        },
        {
          "Card Accepted": "https://im1.dineout.co.in/images/uploads/misc/2019/Jul/1/13.png"
        },
        {
          "Wallet Accepted": "https://im1.dineout.co.in/images/uploads/misc/2019/Jul/1/2.png"
        },
        {
          "Roof Top": "https://im1.dineout.co.in/images/uploads/misc/2019/Jul/1/19.png"
        }
      ],
      "callUs": ["+91 9212340202", "0120-3101000"],
      "reviews": [
        {
          "name": "Dhruv Jindal",
          "star": 5,
          "head": "Liked: Ambience",
          "reviewPost": "Good food"
        },
        {
          "name": "Dr Tushar",
          "star": 3,
          "head": "Liked: Service",
          "reviewPost": "all was awesome !!"
        }
      ]
    },
    {
      "id": 9,
      "city": "Delhi",
      "name": "High 5 - Everyday Wholesale Bar",
      "area": "Central Delhi",
      "address": "Connaught Place",
      "rating": 4.4,
      "image": "https://im1.dineout.co.in/images/uploads/restaurant/sharpen/6/s/m/p69146-163921872761b47e27e5f71.jpg?tr=tr:n-large",
      "discount": 25,
      "about": "High 5 - Everyday Wholesale Bar is a perfect getaway from the mundane flow of life, bringing alive the very essence of the pub culture made famous by the typical pubs of Europe, offering a place to connect with friends, conversations, awesome food and drinks, in an ambiance that lets you relax and go with the flow. This brand new urban spin of pub culture arrives at the capital. Take a trip to The Chatter House, a welcome ambiance that immediately transports you to another level. The outlet is located in Khan Market, Delhi. ",
      "averageCost": "₹ 1,700 for 2",
      "cuisine": ["Continental", "North Indian", "American", "Chinese"],
      "menu": "https://im1.dineout.co.in/images/uploads/restaurant/sharpen/6/r/o/m69146-16444708866204a2669685b.jpg?tr=tr:n-xlarge",
      "type": ["NightLife", "Bar"],
      "bestSellingItems": [
        "Exotic Mushroom",
        "Butter Chicken",
        "Gulab Jamun",
        "Kadhai Paneer",
        "Cottage Chesse Burger",
        "Keema Fries",
        "Blueberry Lemon Cake",
        "Chiken Burger"
      ],
      "facilities": [
        {
          "Smoking Area": "https://im1.dineout.co.in/images/uploads/misc/2019/Jul/1/17.png"
        },
        {
          "Air Conditioned": "https://im1.dineout.co.in/images/uploads/misc/2019/Jul/1/7.png"
        },
        {
          "Valet Available": "https://im1.dineout.co.in/images/uploads/misc/2019/Jul/1/21.png"
        },
        {
          "Card Accepted": "https://im1.dineout.co.in/images/uploads/misc/2019/Jul/1/13.png"
        },
        {
          "Wallet Accepted": "https://im1.dineout.co.in/images/uploads/misc/2019/Jul/1/2.png"
        },
        {
          "Roof Top": "https://im1.dineout.co.in/images/uploads/misc/2019/Jul/1/19.png"
        }
      ],
      "callUs": ["+91 9212340202", "0120-3101000"],
      "reviews": [
        {
          "name": "Dhruv Jindal",
          "star": 5,
          "head": "Liked: Ambience",
          "reviewPost": "Good food"
        },
        {
          "name": "Dr Tushar",
          "star": 3,
          "head": "Liked: Service",
          "reviewPost": "all was awesome !!"
        }
      ]
    },
    {
      "id": 10,
      "city": "Delhi",
      "name": "High 5 - Everyday Wholesale Bar",
      "area": "Central Delhi",
      "address": "Connaught Place",
      "rating": 4.4,
      "image": "https://im1.dineout.co.in/images/uploads/restaurant/sharpen/6/s/m/p69146-163921872761b47e27e5f71.jpg?tr=tr:n-large",
      "discount": 25,
      "about": "High 5 - Everyday Wholesale Bar is a perfect getaway from the mundane flow of life, bringing alive the very essence of the pub culture made famous by the typical pubs of Europe, offering a place to connect with friends, conversations, awesome food and drinks, in an ambiance that lets you relax and go with the flow. This brand new urban spin of pub culture arrives at the capital. Take a trip to The Chatter House, a welcome ambiance that immediately transports you to another level. The outlet is located in Khan Market, Delhi. ",
      "averageCost": "₹ 1,700 for 2",
      "cuisine": ["Continental", "North Indian", "American", "Chinese"],
      "menu": "https://im1.dineout.co.in/images/uploads/restaurant/sharpen/6/r/o/m69146-16444708866204a2669685b.jpg?tr=tr:n-xlarge",
      "type": ["NightLife", "Bar"],
      "bestSellingItems": [
        "Exotic Mushroom",
        "Butter Chicken",
        "Gulab Jamun",
        "Kadhai Paneer",
        "Cottage Chesse Burger",
        "Keema Fries",
        "Blueberry Lemon Cake",
        "Chiken Burger"
      ],
      "facilities": [
        {
          "Smoking Area": "https://im1.dineout.co.in/images/uploads/misc/2019/Jul/1/17.png"
        },
        {
          "Air Conditioned": "https://im1.dineout.co.in/images/uploads/misc/2019/Jul/1/7.png"
        },
        {
          "Valet Available": "https://im1.dineout.co.in/images/uploads/misc/2019/Jul/1/21.png"
        },
        {
          "Card Accepted": "https://im1.dineout.co.in/images/uploads/misc/2019/Jul/1/13.png"
        },
        {
          "Wallet Accepted": "https://im1.dineout.co.in/images/uploads/misc/2019/Jul/1/2.png"
        },
        {
          "Roof Top": "https://im1.dineout.co.in/images/uploads/misc/2019/Jul/1/19.png"
        }
      ],
      "callUs": ["+91 9212340202", "0120-3101000"],
      "reviews": [
        {
          "name": "Dhruv Jindal",
          "star": 5,
          "head": "Liked: Ambience",
          "reviewPost": "Good food"
        },
        {
          "name": "Dr Tushar",
          "star": 3,
          "head": "Liked: Service",
          "reviewPost": "all was awesome !!"
        }
      ]
    }
  ]
}
